MANIFEST.in
README.md
requirements.txt
setup.py
batticon/__init__.py
batticon/batticon.py
batticon/settings.json
batticon.egg-info/PKG-INFO
batticon.egg-info/SOURCES.txt
batticon.egg-info/dependency_links.txt
batticon.egg-info/entry_points.txt
batticon.egg-info/top_level.txt
batticon/themes/baloon/005-discharging.png
batticon/themes/baloon/017-discharging.png
batticon/themes/baloon/029-discharging.png
batticon/themes/baloon/041-discharging.png
batticon/themes/baloon/053-discharging.png
batticon/themes/baloon/065-discharging.png
batticon/themes/baloon/077-discharging.png
batticon/themes/baloon/089-discharging.png
batticon/themes/baloon/100-charging.png
batticon/themes/baloon/100-discharging.png
batticon/themes/baloon/default.png
batticon/themes/faenza/010-discharging.svg
batticon/themes/faenza/040-discharging.svg
batticon/themes/faenza/075-discharging.svg
batticon/themes/faenza/085-charging.svg
batticon/themes/faenza/100-charging.svg
batticon/themes/faenza/100-discharging.svg
batticon/themes/faenza/default.svg
batticon/themes/minimalbatt/000-charging.png
batticon/themes/minimalbatt/000-discharging.png
batticon/themes/minimalbatt/010-discharging.png
batticon/themes/minimalbatt/020-charging.png
batticon/themes/minimalbatt/020-discharging.png
batticon/themes/minimalbatt/030-discharging.png
batticon/themes/minimalbatt/040-charging.png
batticon/themes/minimalbatt/040-discharging.png
batticon/themes/minimalbatt/050-discharging.png
batticon/themes/minimalbatt/060-charging.png
batticon/themes/minimalbatt/060-discharging.png
batticon/themes/minimalbatt/070-discharging.png
batticon/themes/minimalbatt/080-charging.png
batticon/themes/minimalbatt/080-discharging.png
batticon/themes/minimalbatt/090-discharging.png
batticon/themes/minimalbatt/100-charging.png
batticon/themes/minimalbatt/100-discharging.png
batticon/themes/minimalbatt/default.png
batticon/themes/mono-dark/005-charging.svg
batticon/themes/mono-dark/005-discharging.svg
batticon/themes/mono-dark/020-charging.svg
batticon/themes/mono-dark/020-discharging.svg
batticon/themes/mono-dark/040-charging.svg
batticon/themes/mono-dark/040-discharging.svg
