Metadata-Version: 1.0
Name: batticon
Version: 0.1.4
Summary: This is a simple battery indicator for system tray
Home-page: https://github.com/sorrowless/battery_systray
Author: Stanislaw Bogatkin
Author-email: sbog@sbog.ru
License: GPL
Keywords: battery indicator systray system tray
Platform: UNKNOWN
